[
  {
    "posts": [
      "https://forum.leitstellenspiel.de/index.php?thread/2140-allgemeines-script-version-dev-alpha-version-jetzt-auch-f%C3%BCr-opera-safari-und-int/&postID=19980#post19980",
      "https://forum.leitstellenspiel.de/index.php?thread/2140-allgemeines-script-version-dev-alpha-version-jetzt-auch-f%C3%BCr-opera-safari-und-int/&postID=20852#post20852"
    ],
    "url": "http://lstspiel.easy-lst.de/allgemeines_script_lstspiel.user.js"
  },
  {
    "posts": [
      "https://forum.leitstellenspiel.de/index.php?thread/1865-scripting/&postID=16541#post16541"
    ],
    "url": "http://sonstiges.easy-lst.de/fzg-uebersicht.user.js"
  },
  {
    "posts": [
      "https://forum.leitstellenspiel.de/index.php?thread/3593-zwei-monitore/&postID=166337#post166337"
    ],
    "url": "https://github.com/lostdesign/lss-layout-manager/raw/master/lss-layout-manager-auto-update.user.js"
  }
]